Workbook
Name Slicer_Brand: #N/A
Name Slicer_City: #N/A
Name Slicer_Customer_Type: #N/A
Name Slicer_Lead_Source: #N/A
Name Slicer_Retailer: #N/A

Sheet Raw_Data
A1: Customer ID | B1: Date | C1: Week | D1: Day | E1: Weekend | F1: Retailer | G1: City | H1: State | I1: Brand | J1: Model | K1: Fuel Type | L1: Segment | M1: Age Group | N1: Income Band | O1: Customer Type | P1: Lead Source | Q1: Salesperson | R1: Customers Visited | S1: Test Drives | T1: Contracts Offered | U1: Contracts Signed | V1: Conversion Rate (%) | W1: Unit Price (€) | X1: Discount (%) | Y1: Cost Price (€) | Z1: Revenue(€) | AA1: Profit(€) | AB1: Month | AC1: Month Number | AD1: Year | AE1: Weekday Type | AF1: Offer Conversion | AG1: Visit to Test Drive % | AH1: Visit to Signed % | AI1: Average Margin per Signed Contract | AJ1: Column1
A2: CUST_1 | B2: 46055 | C2: Week 1 | D2: Monday | E2: No | F2: Main Auto Hub | G2: Frankfurt | H2: Hesse | I2: BMW | J2: X5 | K2: Hybrid | L2: SUV | M2: 18-25 | N2: Low | O2: Returning | P2: Social Media | Q2: Sales_11 | R2: 153 | S2: 73 | T2: 53 | U2: 18 | V2: 24.66 | W2: 58436 | X2: 2.66 | Y2: 41345 | Z2: 1051848 | AA2: 307638 | AB2: =(VLOOKUP(SalesData[[#This Row],[Month Number]],Reference!C$5:E$16,2,FALSE)) -> Feb | AC2: =MONTH(SalesData[[#This Row],[Date]]) -> 2 | AD2: =Reference!F$4 -> 2026 | AE2: =IF(OR(SalesData[[#This Row],[Day]]="Saturday",SalesData[[#This Row],[Day]]="Sunday"),"Weekend","Weekday") -> Weekday | AF2: =IF(SalesData[[#This Row],[Contracts Offered]]=0,0,SalesData[[#This Row],[Contracts Signed]]/SalesData[[#This Row],[Contracts Offered]]) -> 0.33962264 | AG2: =IF(SalesData[[#This Row],[Customers Visited]]=0,0,SalesData[[#This Row],[Test Drives]]/SalesData[[#This Row],[Customers Visited]]) -> 0.47712418 | AH2: =IF(SalesData[[#This Row],[Customers Visited]]=0,0,SalesData[[#This Row],[Contracts Signed]]/SalesData[[#This Row],[Customers Visited]]) -> 0.11764706 | AI2: =IF(SalesData[[#This Row],[Contracts Signed]]=0,0,SalesData[[#This Row],[Profit(€)]]/SalesData[[#This Row],[Contracts Signed]]) -> 17091 | AJ2: =TRIM(CLEAN(SalesData[[#This Row],[Retailer]])) -> Main Auto Hub
A3: CUST_2 | B3: 46078 | C3: Week 4 | D3: Wednesday | E3: No | F3: Rhein Auto Group | G3: Cologne | H3: NRW | I3: Opel | J3: Mokka | K3: Petrol | L3: SUV | M3: 18-25 | N3: Medium | O3: Returning | P3: Walk-in | Q3: Sales_2 | R3: 243 | S3: 121 | T3: 69 | U3: 24 | V3: 19.83 | W3: 21127 | X3: 13.38 | Y3: 19164 | Z3: 507048 | AA3: 47112 | AB3: =(VLOOKUP(SalesData[[#This Row],[Month Number]],Reference!C$5:E$16,2,FALSE)) -> Feb | AC3: =MONTH(SalesData[[#This Row],[Date]]) -> 2 | AD3: =Reference!F$4 -> 2026 | AE3: =IF(OR(SalesData[[#This Row],[Day]]="Saturday",SalesData[[#This Row],[Day]]="Sunday"),"Weekend","Weekday") -> Weekday | AF3: =IF(SalesData[[#This Row],[Contracts Offered]]=0,0,SalesData[[#This Row],[Contracts Signed]]/SalesData[[#This Row],[Contracts Offered]]) -> 0.34782609 | AG3: =IF(SalesData[[#This Row],[Customers Visited]]=0,0,SalesData[[#This Row],[Test Drives]]/SalesData[[#This Row],[Customers Visited]]) -> 0.49794239 | AH3: =IF(SalesData[[#This Row],[Customers Visited]]=0,0,SalesData[[#This Row],[Contracts Signed]]/SalesData[[#This Row],[Customers Visited]]) -> 0.098765432 | AI3: =IF(SalesData[[#This Row],[Contracts Signed]]=0,0,SalesData[[#This Row],[Profit(€)]]/SalesData[[#This Row],[Contracts Signed]]) -> 1963 | AJ3: =TRIM(CLEAN(SalesData[[#This Row],[Retailer]])) -> Rhein Auto Group
A4: CUST_3 | B4: 46062 | C4: Week 2 | D4: Monday | E4: No | F4: Hannover Cars | G4: Hannover | H4: Lower Saxony | I4: BMW | J4: X3 | K4: Hybrid | L4: SUV | M4: 50+ | N4: Low | O4: Returning | P4: Walk-in | Q4: Sales_13 | R4: 271 | S4: 141 | T4: 106 | U4: 43 | V4: 30.5 | W4: 67568 | X4: 5.56 | Y4: 50075 | Z4: 2905424 | AA4: 752199 | AB4: =(VLOOKUP(SalesData[[#This Row],[Month Number]],Reference!C$5:E$16,2,FALSE)) -> Feb | AC4: =MONTH(SalesData[[#This Row],[Date]]) -> 2 | AD4: =Reference!F$4 -> 2026 | AE4: =IF(OR(SalesData[[#This Row],[Day]]="Saturday",SalesData[[#This Row],[Day]]="Sunday"),"Weekend","Weekday") -> Weekday | AF4: =IF(SalesData[[#This Row],[Contracts Offered]]=0,0,SalesData[[#This Row],[Contracts Signed]]/SalesData[[#This Row],[Contracts Offered]]) -> 0.40566038 | AG4: =IF(SalesData[[#This Row],[Customers Visited]]=0,0,SalesData[[#This Row],[Test Drives]]/SalesData[[#This Row],[Customers Visited]]) -> 0.5202952 | AH4: =IF(SalesData[[#This Row],[Customers Visited]]=0,0,SalesData[[#This Row],[Contracts Signed]]/SalesData[[#This Row],[Customers Visited]]) -> 0.15867159 | AI4: =IF(SalesData[[#This Row],[Contracts Signed]]=0,0,SalesData[[#This Row],[Profit(€)]]/SalesData[[#This Row],[Contracts Signed]]) -> 17493 | AJ4: =TRIM(CLEAN(SalesData[[#This Row],[Retailer]])) -> Hannover Cars
A5: CUST_4 | B5: 46075 | C5: Week 4 | D5: Sunday | E5: Yes | F5: Saxon Wheels | G5: Dresden | H5: Saxony | I5: Audi | J5: e-tron | K5: Petrol | L5: SUV | M5: 26-35 | N5: High | O5: New | P5: Referral | Q5: Sales_9 | R5: 203 | S5: 105 | T5: 75 | U5: 27 | V5: 25.71 | W5: 51246 | X5: 4.83 | Y5: 39966 | Z5: 1383642 | AA5: 304560 | AB5: =(VLOOKUP(SalesData[[#This Row],[Month Number]],Reference!C$5:E$16,2,FALSE)) -> Feb | AC5: =MONTH(SalesData[[#This Row],[Date]]) -> 2 | AD5: =Reference!F$4 -> 2026 | AE5: =IF(OR(SalesData[[#This Row],[Day]]="Saturday",SalesData[[#This Row],[Day]]="Sunday"),"Weekend","Weekday") -> Weekend | AF5: =IF(SalesData[[#This Row],[Contracts Offered]]=0,0,SalesData[[#This Row],[Contracts Signed]]/SalesData[[#This Row],[Contracts Offered]]) -> 0.36 | AG5: =IF(SalesData[[#This Row],[Customers Visited]]=0,0,SalesData[[#This Row],[Test Drives]]/SalesData[[#This Row],[Customers Visited]]) -> 0.51724138 | AH5: =IF(SalesData[[#This Row],[Customers Visited]]=0,0,SalesData[[#This Row],[Contracts Signed]]/SalesData[[#This Row],[Customers Visited]]) -> 0.13300493 | AI5: =IF(SalesData[[#This Row],[Contracts Signed]]=0,0,SalesData[[#This Row],[Profit(€)]]/SalesData[[#This Row],[Contracts Signed]]) -> 11280 | AJ5: =TRIM(CLEAN(SalesData[[#This Row],[Retailer]])) -> Saxon Wheels
A6: CUST_5 | B6: 46064 | C6: Week 2 | D6: Wednesday | E6: No | F6: Autohaus Berlin | G6: Berlin | H6: Berlin | I6: Mercedes | J6: EQE | K6: Petrol | L6: Sedan | M6: 36-50 | N6: Low | O6: Returning | P6: Website | Q6: Sales_13 | R6: 281 | S6: 146 | T6: 113 | U6: 34 | V6: 23.29 | W6: 57760 | X6: 5.97 | Y6: 41176 | Z6: 1963840 | AA6: 563856 | AB6: =(VLOOKUP(SalesData[[#This Row],[Month Number]],Reference!C$5:E$16,2,FALSE)) -> Feb | AC6: =MONTH(SalesData[[#This Row],[Date]]) -> 2 | AD6: =Reference!F$4 -> 2026 | AE6: =IF(OR(SalesData[[#This Row],[Day]]="Saturday",SalesData[[#This Row],[Day]]="Sunday"),"Weekend","Weekday") -> Weekday | AF6: =IF(SalesData[[#This Row],[Contracts Offered]]=0,0,SalesData[[#This Row],[Contracts Signed]]/SalesData[[#This Row],[Contracts Offered]]) -> 0.30088496 | AG6: =IF(SalesData[[#This Row],[Customers Visited]]=0,0,SalesData[[#This Row],[Test Drives]]/SalesData[[#This Row],[Customers Visited]]) -> 0.51957295 | AH6: =IF(SalesData[[#This Row],[Customers Visited]]=0,0,SalesData[[#This Row],[Contracts Signed]]/SalesData[[#This Row],[Customers Visited]]) -> 0.12099644 | AI6: =IF(SalesData[[#This Row],[Contracts Signed]]=0,0,SalesData[[#This Row],[Profit(€)]]/SalesData[[#This Row],[Contracts Signed]]) -> 16584 | AJ6: =TRIM(CLEAN(SalesData[[#This Row],[Retailer]])) -> Autohaus Berlin
A7: CUST_6 | B7: 46074 | C7: Week 3 | D7: Saturday | E7: Yes | F7: Elbe Drive | G7: Hamburg | H7: Hamburg | I7: Opel | J7: Mokka | K7: Diesel | L7: SUV | M7: 26-35 | N7: High | O7: Returning | P7: Referral | Q7: Sales_15 | R7: 231 | S7: 88 | T7: 54 | U7: 15 | V7: 17.05 | W7: 25844 | X7: 9.46 | Y7: 23754 | Z7: 387660 | AA7: 31350 | AB7: =(VLOOKUP(SalesData[[#This Row],[Month Number]],Reference!C$5:E$16,2,FALSE)) -> Feb | AC7: =MONTH(SalesData[[#This Row],[Date]]) -> 2 | AD7: =Reference!F$4 -> 2026 | AE7: =IF(OR(SalesData[[#This Row],[Day]]="Saturday",SalesData[[#This Row],[Day]]="Sunday"),"Weekend","Weekday") -> Weekend | AF7: =IF(SalesData[[#This Row],[Contracts Offered]]=0,0,SalesData[[#This Row],[Contracts Signed]]/SalesData[[#This Row],[Contracts Offered]]) -> 0.27777778 | AG7: =IF(SalesData[[#This Row],[Customers Visited]]=0,0,SalesData[[#This Row],[Test Drives]]/SalesData[[#This Row],[Customers Visited]]) -> 0.38095238 | AH7: =IF(SalesData[[#This Row],[Customers Visited]]=0,0,SalesData[[#This Row],[Contracts Signed]]/SalesData[[#This Row],[Customers Visited]]) -> 0.064935065 | AI7: =IF(SalesData[[#This Row],[Contracts Signed]]=0,0,SalesData[[#This Row],[Profit(€)]]/SalesData[[#This Row],[Contracts Signed]]) -> 2090 | AJ7: =TRIM(CLEAN(SalesData[[#This Row],[Retailer]])) -> Elbe Drive
A8: CUST_7 | B8: 46067 | C8: Week 2 | D8: Saturday | E8: Yes | F8: Saxon Wheels | G8: Dresden | H8: Saxony | I8: BMW | J8: 3 Series | K8: Petrol | L8: Sedan | M8: 36-50 | N8: High | O8: New | P8: Walk-in | Q8: Sales_14 | R8: 142 | S8: 83 | T8: 60 | U8: 22 | V8: 26.51 | W8: 63862 | X8: 2.12 | Y8: 48165 | Z8: 1404964 | AA8: 345334 | AB8: =(VLOOKUP(SalesData[[#This Row],[Month Number]],Reference!C$5:E$16,2,FALSE)) -> Feb | AC8: =MONTH(SalesData[[#This Row],[Date]]) -> 2 | AD8: =Reference!F$4 -> 2026 | AE8: =IF(OR(SalesData[[#This Row],[Day]]="Saturday",SalesData[[#This Row],[Day]]="Sunday"),"Weekend","Weekday") -> Weekend | AF8: =IF(SalesData[[#This Row],[Contracts Offered]]=0,0,SalesData[[#This Row],[Contracts Signed]]/SalesData[[#This Row],[Contracts Offered]]) -> 0.36666667 | AG8: =IF(SalesData[[#This Row],[Customers Visited]]=0,0,SalesData[[#This Row],[Test Drives]]/SalesData[[#This Row],[Customers Visited]]) -> 0.58450704 | AH8: =IF(SalesData[[#This Row],[Customers Visited]]=0,0,SalesData[[#This Row],[Contracts Signed]]/SalesData[[#This Row],[Customers Visited]]) -> 0.15492958 | AI8: =IF(SalesData[[#This Row],[Contracts Signed]]=0,0,SalesData[[#This Row],[Profit(€)]]/SalesData[[#This Row],[Contracts Signed]]) -> 15697 | AJ8: =TRIM(CLEAN(SalesData[[#This Row],[Retailer]])) -> Saxon Wheels
A9: CUST_8 | B9: 46069 | C9: Week 3 | D9: Monday | E9: No | F9: Autohaus Berlin | G9: Berlin | H9: Berlin | I9: Opel | J9: Grandland | K9: Electric | L9: SUV | M9: 36-50 | N9: Low | O9: New | P9: Referral | Q9: Sales_3 | R9: 403 | S9: 216 | T9: 125 | U9: 45 | V9: 20.83 | W9: 25974 | X9: 7.55 | Y9: 23243 | Z9: 1168830 | AA9: 122895 | AB9: =(VLOOKUP(SalesData[[#This Row],[Month Number]],Reference!C$5:E$16,2,FALSE)) -> Feb | AC9: =MONTH(SalesData[[#This Row],[Date]]) -> 2 | AD9: =Reference!F$4 -> 2026 | AE9: =IF(OR(SalesData[[#This Row],[Day]]="Saturday",SalesData[[#This Row],[Day]]="Sunday"),"Weekend","Weekday") -> Weekday | AF9: =IF(SalesData[[#This Row],[Contracts Offered]]=0,0,SalesData[[#This Row],[Contracts Signed]]/SalesData[[#This Row],[Contracts Offered]]) -> 0.36 | AG9: =IF(SalesData[[#This Row],[Customers Visited]]=0,0,SalesData[[#This Row],[Test Drives]]/SalesData[[#This Row],[Customers Visited]]) -> 0.53598015 | AH9: =IF(SalesData[[#This Row],[Customers Visited]]=0,0,SalesData[[#This Row],[Contracts Signed]]/SalesData[[#This Row],[Customers Visited]]) -> 0.11166253 | AI9: =IF(SalesData[[#This Row],[Contracts Signed]]=0,0,SalesData[[#This Row],[Profit(€)]]/SalesData[[#This Row],[Contracts Signed]]) -> 2731 | AJ9: =TRIM(CLEAN(SalesData[[#This Row],[Retailer]])) -> Autohaus Berlin
A10: CUST_9 | B10: 46055 | C10: Week 1 | D10: Monday | E10: No | F10: Leipzig Mobility | G10: Leipzig | H10: Saxony | I10: VW | J10: T-Roc | K10: Hybrid | L10: SUV | M10: 26-35 | N10: High | O10: Returning | P10: Referral | Q10: Sales_12 | R10: 324 | S10: 160 | T10: 100 | U10: 26 | V10: 16.25 | W10: 27410 | X10: 10.81 | Y10: 24414 | Z10: 712660 | AA10: 77896 | AB10: =(VLOOKUP(SalesData[[#This Row],[Month Number]],Reference!C$5:E$16,2,FALSE)) -> Feb | AC10: =MONTH(SalesData[[#This Row],[Date]]) -> 2 | AD10: =Reference!F$4 -> 2026 | AE10: =IF(OR(SalesData[[#This Row],[Day]]="Saturday",SalesData[[#This Row],[Day]]="Sunday"),"Weekend","Weekday") -> Weekday | AF10: =IF(SalesData[[#This Row],[Contracts Offered]]=0,0,SalesData[[#This Row],[Contracts Signed]]/SalesData[[#This Row],[Contracts Offered]]) -> 0.26 | AG10: =IF(SalesData[[#This Row],[Customers Visited]]=0,0,SalesData[[#This Row],[Test Drives]]/SalesData[[#This Row],[Customers Visited]]) -> 0.49382716 | AH10: =IF(SalesData[[#This Row],[Customers Visited]]=0,0,SalesData[[#This Row],[Contracts Signed]]/SalesData[[#This Row],[Customers Visited]]) -> 0.080246914 | AI10: =IF(SalesData[[#This Row],[Contracts Signed]]=0,0,SalesData[[#This Row],[Profit(€)]]/SalesData[[#This Row],[Contracts Signed]]) -> 2996 | AJ10: =TRIM(CLEAN(SalesData[[#This Row],[Retailer]])) -> Leipzig Mobility
A11: CUST_10 | B11: 46055 | C11: Week 1 | D11: Monday | E11: No | F11: Bavaria Motors | G11: Munich | H11: Bavaria | I11: VW | J11: Golf | K11: Hybrid | L11: Hatchback | M11: 50+ | N11: High | O11: Returning | P11: Social Media | Q11: Sales_14 | R11: 274 | S11: 117 | T11: 73 | U11: 19 | V11: 16.24 | W11: 34587 | X11: 6.82 | Y11: 30609 | Z11: 657153 | AA11: 75582 | AB11: =(VLOOKUP(SalesData[[#This Row],[Month Number]],Reference!C$5:E$16,2,FALSE)) -> Feb | AC11: =MONTH(SalesData[[#This Row],[Date]]) -> 2 | AD11: =Reference!F$4 -> 2026 | AE11: =IF(OR(SalesData[[#This Row],[Day]]="Saturday",SalesData[[#This Row],[Day]]="Sunday"),"Weekend","Weekday") -> Weekday | AF11: =IF(SalesData[[#This Row],[Contracts Offered]]=0,0,SalesData[[#This Row],[Contracts Signed]]/SalesData[[#This Row],[Contracts Offered]]) -> 0.26027397 | AG11: =IF(SalesData[[#This Row],[Customers Visited]]=0,0,SalesData[[#This Row],[Test Drives]]/SalesData[[#This Row],[Customers Visited]]) -> 0.4270073 | AH11: =IF(SalesData[[#This Row],[Customers Visited]]=0,0,SalesData[[#This Row],[Contracts Signed]]/SalesData[[#This Row],[Customers Visited]]) -> 0.069343066 | AI11: =IF(SalesData[[#This Row],[Contracts Signed]]=0,0,SalesData[[#This Row],[Profit(€)]]/SalesData[[#This Row],[Contracts Signed]]) -> 3978 | AJ11: =TRIM(CLEAN(SalesData[[#This Row],[Retailer]])) -> Bavaria Motors
A12: CUST_11 | B12: 46071 | C12: Week 3 | D12: Wednesday | E12: No | F12: Stuttgart Auto Center | G12: Stuttgart | H12: Baden-WÃ¼rttemberg | I12: Mercedes | J12: EQE | K12: Hybrid | L12: Sedan | M12: 18-25 | N12: Medium | O12: New | P12: Website | Q12: Sales_11 | R12: 212 | S12: 106 | T12: 83 | U12: 23 | V12: 21.7 | W12: 56108 | X12: 4.02 | Y12: 40922 | Z12: 1290484 | AA12: 349278 | AB12: =(VLOOKUP(SalesData[[#This Row],[Month Number]],Reference!C$5:E$16,2,FALSE)) -> Feb | AC12: =MONTH(SalesData[[#This Row],[Date]]) -> 2 | AD12: =Reference!F$4 -> 2026 | AE12: =IF(OR(SalesData[[#This Row],[Day]]="Saturday",SalesData[[#This Row],[Day]]="Sunday"),"Weekend","Weekday") -> Weekday | AF12: =IF(SalesData[[#This Row],[Contracts Offered]]=0,0,SalesData[[#This Row],[Contracts Signed]]/SalesData[[#This Row],[Contracts Offered]]) -> 0.27710843 | AG12: =IF(SalesData[[#This Row],[Customers Visited]]=0,0,SalesData[[#This Row],[Test Drives]]/SalesData[[#This Row],[Customers Visited]]) -> 0.5 | AH12: =IF(SalesData[[#This Row],[Customers Visited]]=0,0,SalesData[[#This Row],[Contracts Signed]]/SalesData[[#This Row],[Customers Visited]]) -> 0.10849057 | AI12: =IF(SalesData[[#This Row],[Contracts Signed]]=0,0,SalesData[[#This Row],[Profit(€)]]/SalesData[[#This Row],[Contracts Signed]]) -> 15186 | AJ12: =TRIM(CLEAN(SalesData[[#This Row],[Retailer]])) -> Stuttgart Auto Center
A13: CUST_12 | B13: 46054 | C13: Week 1 | D13: Sunday | E13: Yes | F13: Elbe Drive | G13: Hamburg | H13: Hamburg | I13: Audi | J13: e-tron | K13: Diesel | L13: SUV | M13: 18-25 | N13: High | O13: Returning | P13: Walk-in | Q13: Sales_11 | R13: 301 | S13: 167 | T13: 128 | U13: 44 | V13: 26.35 | W13: 48955 | X13: 3.54 | Y13: 37052 | Z13: 2154020 | AA13: 523732 | AB13: =(VLOOKUP(SalesData[[#This Row],[Month Number]],Reference!C$5:E$16,2,FALSE)) -> Feb | AC13: =MONTH(SalesData[[#This Row],[Date]]) -> 2 | AD13: =Reference!F$4 -> 2026 | AE13: =IF(OR(SalesData[[#This Row],[Day]]="Saturday",SalesData[[#This Row],[Day]]="Sunday"),"Weekend","Weekday") -> Weekend | AF13: =IF(SalesData[[#This Row],[Contracts Offered]]=0,0,SalesData[[#This Row],[Contracts Signed]]/SalesData[[#This Row],[Contracts Offered]]) -> 0.34375 | AG13: =IF(SalesData[[#This Row],[Customers Visited]]=0,0,SalesData[[#This Row],[Test Drives]]/SalesData[[#This Row],[Customers Visited]]) -> 0.55481728 | AH13: =IF(SalesData[[#This Row],[Customers Visited]]=0,0,SalesData[[#This Row],[Contracts Signed]]/SalesData[[#This Row],[Customers Visited]]) -> 0.1461794 | AI13: =IF(SalesData[[#This Row],[Contracts Signed]]=0,0,SalesData[[#This Row],[Profit(€)]]/SalesData[[#This Row],[Contracts Signed]]) -> 11903 | AJ13: =TRIM(CLEAN(SalesData[[#This Row],[Retailer]])) -> Elbe Drive
... A5001: CUST_5000 | B5001: 46064 | C5001: Week 2 | D5001: Wednesday | E5001: No | F5001: Autohaus Berlin | G5001: Berlin | H5001: Berlin | I5001: VW | J5001: ID.4 | K5001: Electric | L5001: SUV | M5001: 26-35 | N5001: Low | O5001: Returning | P5001: Website | Q5001: Sales_2 | R5001: 343 | S5001: 190 | T5001: 116 | U5001: 28 | V5001: 14.74 | W5001: 28919 | X5001: 8.89 | Y5001: 25408 | Z5001: 809732 | AA5001: 98308 | AB5001: =(VLOOKUP(SalesData[[#This Row],[Month Number]],Reference!C$5:E$16,2,FALSE)) -> Feb | AC5001: =MONTH(SalesData[[#This Row],[Date]]) -> 2 | AD5001: =Reference!F$4 -> 2026 | AE5001: =IF(OR(SalesData[[#This Row],[Day]]="Saturday",SalesData[[#This Row],[Day]]="Sunday"),"Weekend","Weekday") -> Weekday | AF5001: =IF(SalesData[[#This Row],[Contracts Offered]]=0,0,SalesData[[#This Row],[Contracts Signed]]/SalesData[[#This Row],[Contracts Offered]]) -> 0.24137931 | AG5001: =IF(SalesData[[#This Row],[Customers Visited]]=0,0,SalesData[[#This Row],[Test Drives]]/SalesData[[#This Row],[Customers Visited]]) -> 0.55393586 | AH5001: =IF(SalesData[[#This Row],[Customers Visited]]=0,0,SalesData[[#This Row],[Contracts Signed]]/SalesData[[#This Row],[Customers Visited]]) -> 0.081632653 | AI5001: =IF(SalesData[[#This Row],[Contracts Signed]]=0,0,SalesData[[#This Row],[Profit(€)]]/SalesData[[#This Row],[Contracts Signed]]) -> 3511 | AJ5001: =TRIM(CLEAN(SalesData[[#This Row],[Retailer]])) -> Autohaus Berlin

Sheet Reference
C4: 1 | D4: Jan | E4: January | F4: 2026
C5: 2 | D5: Feb | E5: February
C6: 3 | D6: Mar | E6: March
C7: 4 | D7: Apr | E7: April
C8: 5 | D8: May | E8: May
C9: 6 | D9: Jun | E9: June
C10: 7 | D10: Jul | E10: July
C11: 8 | D11: Aug | E11: August
C12: 9 | D12: Sep | E12: September
C13: 10 | D13: Oct | E13: October
C14: 11 | D14: Nov | E14: November
C15: 12 | D15: Dec | E15: December

Sheet Pivot_Calcs
A1: Sum of Customers Visited | B1: Sum of Test Drives | C1: Sum of Contracts Signed | D1: Sum of Revenue(€) | E1: Sum of Profit(€) | G1: KPI Calculation Block | J1: Stage | K1: Value
A2: 346287 | B2: 174667 | C2: 33623 | D2: 1495473561 | E2: 316495279 | G2: Total Customers | H2: =GETPIVOTDATA("Sum of Customers Visited",$A$1) -> 346287 | J2: Customers Visited | K2: =GETPIVOTDATA("Sum of Customers Visited",$A$4) -> 346287
G3: Total Test Drives | H3: =GETPIVOTDATA("Sum of Test Drives",$A$1) -> 174667 | J3: Test Drives | K3: =GETPIVOTDATA("Sum of Test Drives",$A$4) -> 174667
A4: Sum of Customers Visited | B4: Sum of Test Drives | C4: Sum of Contracts Offered | D4: Sum of Contracts Signed | G4: Total Contracts | H4: =GETPIVOTDATA("Sum of Contracts Signed",$A$1) -> 33623 | J4: Contracts Offered | K4: =GETPIVOTDATA("Sum of Contracts Offered",$A$4) -> 118703
A5: 346287 | B5: 174667 | C5: 118703 | D5: 33623 | G5: Total Revenue | H5: =GETPIVOTDATA("Sum of Revenue(€)",$A$1) -> 1495473561 | J5: Contracts Signed | K5: =GETPIVOTDATA("Sum of Contracts Signed",$A$4) -> 33623
G6: Total Profit | H6: =GETPIVOTDATA("Sum of Profit(€)",$A$1) -> 316495279
A7: Row Labels | B7: Sum of Profit(€) | G7: Conversion Rate | H7: =GETPIVOTDATA("Sum of Contracts Signed",$A$1)/GETPIVOTDATA("Sum of Test Drives",$A$1) -> 0.19249772
A8: Week 1 | B8: 81437076
A9: Week 2 | B9: 81816712 | D9: Row Labels | E9: Sum of Revenue(€) | F9: Sum of Profit(€) | G9: Sum of Contracts Signed | H9: Sum of Test Drives | I9: Row Labels | J9: Sum of Revenue(€) | K9: Sum of Profit(€) | L9: Conversion Rate (%)
A10: Week 3 | B10: 81600568 | D10: Audi | E10: 354430918 | F10: 77125182 | G10: 7473 | H10: 34274 | I10: Audi | J10: =GETPIVOTDATA("Sum of Revenue(€)",$D$9,"Brand","Audi") -> 354430918 | K10: =GETPIVOTDATA("Sum of Profit(€)",$D$9,"Brand","Audi") -> 77125182 | L10: =GETPIVOTDATA("Sum of Contracts Signed",$D$9,"Brand","Audi")/GETPIVOTDATA("Sum of Test Drives",$D$9,"Brand","Audi") -> 0.218037
A11: Week 4 | B11: 71640923 | D11: BMW | E11: 411909738 | F11: 107677516 | G11: 6872 | H11: 25817 | I11: BMW | J11: =GETPIVOTDATA("Sum of Revenue(€)",$D$9,"Brand","BMW") -> 411909738 | K11: =GETPIVOTDATA("Sum of Profit(€)",$D$9,"Brand","BMW") -> 107677516 | L11: =GETPIVOTDATA("Sum of Contracts Signed",$D$9,"Brand","BMW")/GETPIVOTDATA("Sum of Test Drives",$D$9,"Brand","BMW") -> 0.2661812
A12: Grand Total | B12: 316495279 | D12: Mercedes | E12: 374773721 | F12: 94095197 | G12: 6175 | H12: 26004 | I12: Mercedes | J12: =GETPIVOTDATA("Sum of Revenue(€)",$D$9,"Brand","Mercedes") -> 374773721 | K12: =GETPIVOTDATA("Sum of Profit(€)",$D$9,"Brand","Mercedes") -> 94095197 | L12: =GETPIVOTDATA("Sum of Contracts Signed",$D$9,"Brand","Mercedes")/GETPIVOTDATA("Sum of Test Drives",$D$9,"Brand","Mercedes") -> 0.23746347
D13: Opel | E13: 134733187 | F13: 12126385 | G13: 5776 | H13: 38904 | I13: Opel | J13: =GETPIVOTDATA("Sum of Revenue(€)",$D$9,"Brand","Opel") -> 134733187 | K13: =GETPIVOTDATA("Sum of Profit(€)",$D$9,"Brand","Opel") -> 12126385 | L13: =GETPIVOTDATA("Sum of Contracts Signed",$D$9,"Brand","Opel")/GETPIVOTDATA("Sum of Test Drives",$D$9,"Brand","Opel") -> 0.14846802
A14: Row Labels | B14: Sum of Contracts Signed | D14: VW | E14: 219625997 | F14: 25470999 | G14: 7327 | H14: 49668 | I14: VW | J14: =GETPIVOTDATA("Sum of Revenue(€)",$D$9,"Brand","VW") -> 219625997 | K14: =GETPIVOTDATA("Sum of Profit(€)",$D$9,"Brand","VW") -> 25470999 | L14: =GETPIVOTDATA("Sum of Contracts Signed",$D$9,"Brand","VW")/GETPIVOTDATA("Sum of Test Drives",$D$9,"Brand","VW") -> 0.14751953
A15: Week 1 | B15: 8373 | D15: Grand Total | E15: 1495473561 | F15: 316495279 | G15: 33623 | H15: 174667 | I15: Grand Total | J15: =GETPIVOTDATA("Sum of Revenue(€)",$D$9) -> 1495473561 | K15: =GETPIVOTDATA("Sum of Profit(€)",$D$9) -> 316495279 | L15: =GETPIVOTDATA("Sum of Contracts Signed",$D$9)/GETPIVOTDATA("Sum of Test Drives",$D$9) -> 0.19249772
A16: Week 2 | B16: 8709
A17: Week 3 | B17: 8640 | D17: Row Labels | E17: Sum of Revenue(€) | F17: Sum of Profit(€) | G17: Sum of Contracts Signed | H17: Sum of Test Drives | I17: Row Labels | J17: Sum of Revenue(€) | K17: Sum of Profit(€) | L17: Conversion Rate (%)
A18: Week 4 | B18: 7901 | D18: Bavaria Motors | E18: 164867367 | F18: 35685196 | G18: 3628 | H18: 16784 | I18: Autohaus Berlin | J18: =GETPIVOTDATA("Sum of Revenue(€)",$D$17,"Retailer","AutoHaus Berlin") -> 167063743 | K18: =GETPIVOTDATA("Sum of Profit(€)",$D$17,"Retailer","AutoHaus Berlin") -> 35035559 | L18: =GETPIVOTDATA("Sum of Contracts Signed",$D$17,"Retailer","AutoHaus Berlin")/GETPIVOTDATA("Sum of Test Drives",$D$17,"Retailer","AutoHaus Berlin") -> 0.20419188
A19: Grand Total | B19: 33623 | D19: Elbe Drive | E19: 176133274 | F19: 37136696 | G19: 3977 | H19: 19761 | I19: Bavaria Motors | J19: =GETPIVOTDATA("Sum of Revenue(€)",$D$17,"Retailer","Bavaria Motors") -> 164867367 | K19: =GETPIVOTDATA("Sum of Profit(€)",$D$17,"Retailer","Bavaria Motors") -> 35685196 | L19: =GETPIVOTDATA("Sum of Contracts Signed",$D$17,"Retailer","Bavaria Motors")/GETPIVOTDATA("Sum of Test Drives",$D$17,"Retailer","Bavaria Motors") -> 0.21615825
D20: Hannover Cars | E20: 158668449 | F20: 34653671 | G20: 3422 | H20: 17664 | I20: Elbe Drive | J20: =GETPIVOTDATA("Sum of Revenue(€)",$D$17,"Retailer","Elbe Drive") -> 176133274 | K20: =GETPIVOTDATA("Sum of Profit(€)",$D$17,"Retailer","Elbe Drive") -> 37136696 | L20: =GETPIVOTDATA("Sum of Contracts Signed",$D$17,"Retailer","Elbe Drive")/GETPIVOTDATA("Sum of Test Drives",$D$17,"Retailer","Elbe Drive") -> 0.201255
A21: Row Labels | B21: Sum of Profit(€) | D21: Leipzig Mobility | E21: 130379673 | F21: 27471752 | G21: 2999 | H21: 16744 | I21: Hannover Cars | J21: =GETPIVOTDATA("Sum of Revenue(€)",$D$17,"Retailer","Hannover Cars") -> 158668449 | K21: =GETPIVOTDATA("Sum of Profit(€)",$D$17,"Retailer","Hannover Cars") -> 34653671 | L21: =GETPIVOTDATA("Sum of Contracts Signed",$D$17,"Retailer","Hannover Cars")/GETPIVOTDATA("Sum of Test Drives",$D$17,"Retailer","Hannover Cars") -> 0.19372736
A22: Week 1 | B22: =GETPIVOTDATA("Profit(€)",$A$7,"Week","Week 1") -> 81437076 | D22: Main Auto Hub | E22: 126237997 | F22: 26439864 | G22: 2893 | H22: 15840 | I22: Leipzig Mobility | J22: =GETPIVOTDATA("Sum of Revenue(€)",$D$17,"Retailer","Leipzig Mobility") -> 130379673 | K22: =GETPIVOTDATA("Sum of Profit(€)",$D$17,"Retailer","Leipzig Mobility") -> 27471752 | L22: =GETPIVOTDATA("Sum of Contracts Signed",$D$17,"Retailer","Leipzig Mobility")/GETPIVOTDATA("Sum of Test Drives",$D$17,"Retailer","Leipzig Mobility") -> 0.17910893
A23: Week 2 | B23: =GETPIVOTDATA("Profit(€)",$A$7,"Week","Week 2") -> 81816712 | D23: Rhein Auto Group | E23: 167013952 | F23: 35686202 | G23: 3665 | H23: 18554 | I23: Main Auto Hub | J23: =GETPIVOTDATA("Sum of Revenue(€)",$D$17,"Retailer","Main Auto Hub") -> 126237997 | K23: =GETPIVOTDATA("Sum of Profit(€)",$D$17,"Retailer","Main Auto Hub") -> 26439864 | L23: =GETPIVOTDATA("Sum of Contracts Signed",$D$17,"Retailer","Main Auto Hub")/GETPIVOTDATA("Sum of Test Drives",$D$17,"Retailer","Main Auto Hub") -> 0.18263889
A24: Week 3 | B24: =GETPIVOTDATA("Profit(€)",$A$7,"Week","Week 3") -> 81600568 | D24: Ruhr Auto Plaza | E24: 126704559 | F24: 26435665 | G24: 2906 | H24: 17036 | I24: Rhein Auto Group | J24: =GETPIVOTDATA("Sum of Revenue(€)",$D$17,"Retailer","Rhein Auto Group") -> 167013952 | K24: =GETPIVOTDATA("Sum of Profit(€)",$D$17,"Retailer","Rhein Auto Group") -> 35686202 | L24: =GETPIVOTDATA("Sum of Contracts Signed",$D$17,"Retailer","Rhein Auto Group")/GETPIVOTDATA("Sum of Test Drives",$D$17,"Retailer","Rhein Auto Group") -> 0.19753153
A25: Week 4 | B25: =GETPIVOTDATA("Profit(€)",$A$7,"Week","Week 4") -> 71640923 | D25: Saxon Wheels | E25: 133173778 | F25: 27859557 | G25: 3025 | H25: 16829 | I25: Ruhr Auto Plaza | J25: =GETPIVOTDATA("Sum of Revenue(€)",$D$17,"Retailer","Ruhr Auto Plaza") -> 126704559 | K25: =GETPIVOTDATA("Sum of Profit(€)",$D$17,"Retailer","Ruhr Auto Plaza") -> 26435665 | L25: =GETPIVOTDATA("Sum of Contracts Signed",$D$17,"Retailer","Ruhr Auto Plaza")/GETPIVOTDATA("Sum of Test Drives",$D$17,"Retailer","Ruhr Auto Plaza") -> 0.17057995
D26: Stuttgart Auto Center | E26: 145230769 | F26: 30091117 | G26: 3328 | H26: 16943 | I26: Saxon Wheels | J26: =GETPIVOTDATA("Sum of Revenue(€)",$D$17,"Retailer","Saxon Wheels") -> 133173778 | K26: =GETPIVOTDATA("Sum of Profit(€)",$D$17,"Retailer","Saxon Wheels") -> 27859557 | L26: =GETPIVOTDATA("Sum of Contracts Signed",$D$17,"Retailer","Saxon Wheels")/GETPIVOTDATA("Sum of Test Drives",$D$17,"Retailer","Saxon Wheels") -> 0.17974924
D27: Autohaus Berlin | E27: 167063743 | F27: 35035559 | G27: 3780 | H27: 18512 | I27: Stuttgart Auto Center | J27: =GETPIVOTDATA("Sum of Revenue(€)",$D$17,"Retailer","Stuttgart Auto Center") -> 145230769 | K27: =GETPIVOTDATA("Sum of Profit(€)",$D$17,"Retailer","Stuttgart Auto Center") -> 30091117 | L27: =GETPIVOTDATA("Sum of Contracts Signed",$D$17,"Retailer","Stuttgart Auto Center")/GETPIVOTDATA("Sum of Test Drives",$D$17,"Retailer","Stuttgart Auto Center") -> 0.1964233
D28: Grand Total | E28: 1495473561 | F28: 316495279 | G28: 33623 | H28: 174667 | I28: Grand Total | J28: =GETPIVOTDATA("Sum of Revenue(€)",$D$17) -> 1495473561 | K28: =GETPIVOTDATA("Sum of Profit(€)",$D$17) -> 316495279 | L28: =GETPIVOTDATA("Sum of Contracts Signed",$D$17)/GETPIVOTDATA("Sum of Test Drives",$D$17) -> 0.19249772
A31: Row Labels | B31: Sum of Customers Visited | C31: Sum of Test Drives | D31: Sum of Contracts Signed | G31: Row Labels | H31: Sum of Customers Visited | I31: Conversion %
A32: Website | B32: 346287 | C32: 174667 | D32: 33623 | G32: Referral | H32: =GETPIVOTDATA("Sum of Customers Visited",$A$31,"Lead Source","Referral") -> #REF! | I32: =GETPIVOTDATA("Sum of Contracts Signed",$A$31,"Lead Source","Referral")/GETPIVOTDATA("Sum of Test Drives",$A$31,"Lead Source","Referral") -> #REF!
A33: Grand Total | B33: 346287 | C33: 174667 | D33: 33623 | G33: Social Media | H33: =GETPIVOTDATA("Sum of Customers Visited",$A$31,"Lead Source","Social Media") -> #REF! | I33: =GETPIVOTDATA("Sum of Contracts Signed",$A$31,"Lead Source","Social Media")/GETPIVOTDATA("Sum of Test Drives",$A$31,"Lead Source","Social Media") -> #REF!
G34: Walk-in | H34: =GETPIVOTDATA("Sum of Customers Visited",$A$31,"Lead Source","Walk-in") -> #REF! | I34: =GETPIVOTDATA("Sum of Contracts Signed",$A$31,"Lead Source","Walk-in")/GETPIVOTDATA("Sum of Test Drives",$A$31,"Lead Source","Walk-in") -> #REF!
G35: Website | H35: =GETPIVOTDATA("Sum of Customers Visited",$A$31,"Lead Source","Website") -> 346287 | I35: =GETPIVOTDATA("Sum of Contracts Signed",$A$31,"Lead Source","Website")/GETPIVOTDATA("Sum of Test Drives",$A$31,"Lead Source","Website") -> 0.19249772
G36: Grand Total | H36: =GETPIVOTDATA("Sum of Customers Visited",$A$31) -> 346287 | I36: =GETPIVOTDATA("Sum of Contracts Signed",$A$31)/GETPIVOTDATA("Sum of Test Drives",$A$31) -> 0.19249772
A39: Row Labels | B39: Sum of Revenue(€) | C39: Sum of Profit(€) | D39: Sum of Contracts Signed | E39: Sum of Test Drives | F39: Row Labels | G39: Sum of Revenue(€) | H39: Sum of Profit(€) | I39: Conversion Rate (%)
A40: Hatchback | B40: 172216346 | C40: 24634200 | D40: 5591 | E40: 34876 | F40: Hatchback | G40: =GETPIVOTDATA("Sum of Revenue(€)",$A$39,"Segment","Hatchback") -> 172216346 | H40: =GETPIVOTDATA("Sum of Profit(€)",$A$39,"Segment","Hatchback") -> 24634200 | I40: =GETPIVOTDATA("Sum of Contracts Signed",$A$39,"Segment","Hatchback")/GETPIVOTDATA("Sum of Test Drives",$A$39,"Segment","Hatchback") -> 0.16031082
A41: Sedan | B41: 549909654 | C41: 132176073 | D41: 10101 | E41: 45025 | F41: Sedan | G41: =GETPIVOTDATA("Sum of Revenue(€)",$A$39,"Segment","Sedan") -> 549909654 | H41: =GETPIVOTDATA("Sum of Profit(€)",$A$39,"Segment","Sedan") -> 132176073 | I41: =GETPIVOTDATA("Sum of Contracts Signed",$A$39,"Segment","Sedan")/GETPIVOTDATA("Sum of Test Drives",$A$39,"Segment","Sedan") -> 0.22434203
A42: SUV | B42: 773347561 | C42: 159685006 | D42: 17931 | E42: 94766 | F42: SUV | G42: =GETPIVOTDATA("Sum of Revenue(€)",$A$39,"Segment","SUV") -> 773347561 | H42: =GETPIVOTDATA("Sum of Profit(€)",$A$39,"Segment","SUV") -> 159685006 | I42: =GETPIVOTDATA("Sum of Contracts Signed",$A$39,"Segment","SUV")/GETPIVOTDATA("Sum of Test Drives",$A$39,"Segment","SUV") -> 0.18921343
A43: Grand Total | B43: 1495473561 | C43: 316495279 | D43: 33623 | E43: 174667

Sheet Dashboard
B2: Automotive Dashboard | D2: Sales Performance (February 2026)
B4: =GETPIVOTDATA("Sum of Customers Visited",Pivot_Calcs!$A$1) -> 346287 | C4: =GETPIVOTDATA("Sum of Test Drives",Pivot_Calcs!$A$1) -> 174667 | D4: =GETPIVOTDATA("Sum of Contracts Signed",Pivot_Calcs!$A$1) -> 33623 | E4: =GETPIVOTDATA("Sum of Revenue(€)",Pivot_Calcs!$A$1) -> 1495473561 | F4: =GETPIVOTDATA("Sum of Profit(€)",Pivot_Calcs!$A$1) -> 316495279 | G4: =Pivot_Calcs!H7 -> 0.19249772
B5: Customers | C5: Test Drives | D5: Contracts | E5: Revenue | F5: Profit | G5: Conversion
